madgui/__init__.py
madgui/__main__.py
madgui/core/__init__.py
madgui/core/app.py
madgui/core/config.py
madgui/core/session.py
madgui/data/COPYING.txt
madgui/data/__init__.py
madgui/data/config.yml
madgui/data/icon.xpm
madgui/data/madx_units.yml
madgui/data/style.css
madgui/data/target.xpm
madgui/data/ui_units.yml
madgui/model/__init__.py
madgui/model/errors.py
madgui/model/madx.py
madgui/model/match.py
madgui/online/__init__.py
madgui/online/api.py
madgui/online/control.py
madgui/online/diagnostic.py
madgui/online/dialogs.py
madgui/online/emittance.ui
madgui/online/monitorwidget.ui
madgui/online/offcal.py
madgui/online/offcal.ui
madgui/online/offsetswidget.ui
madgui/online/orbit.py
madgui/online/orm_measure.py
madgui/online/orm_measure.ui
madgui/online/procedure.py
madgui/plot/__init__.py
madgui/plot/scene.py
madgui/plot/twissfigure.py
madgui/plot/twissfigure.yml
madgui/survey/__init__.py
madgui/survey/camera.py
madgui/survey/gl_util.py
madgui/survey/gl_widget.py
madgui/survey/shader_fragment.glsl
madgui/survey/shader_vertex.glsl
madgui/survey/shapes.py
madgui/survey/transform.py
madgui/survey/widget.py
madgui/util/__init__.py
madgui/util/collections.py
madgui/util/enum.py
madgui/util/export.py
madgui/util/fit.py
madgui/util/history.py
madgui/util/layout.py
madgui/util/menu.py
madgui/util/misc.py
madgui/util/qt.py
madgui/util/signal.py
madgui/util/table.py
madgui/util/undo.py
madgui/util/unit.py
madgui/util/yaml.py
madgui/widget/__init__.py
madgui/widget/about.py
madgui/widget/about.ui
madgui/widget/curvemanager.py
madgui/widget/curvemanager.ui
madgui/widget/dialog.py
madgui/widget/edit.py
madgui/widget/elementinfo.py
madgui/widget/filedialog.py
madgui/widget/floor_plan.py
madgui/widget/log.py
madgui/widget/mainwindow.py
madgui/widget/mainwindow.ui
madgui/widget/match.py
madgui/widget/match.ui
madgui/widget/params.py
madgui/widget/plot.py
madgui/widget/pyshell.py
madgui/widget/quantity.py
madgui/widget/spinbox.py
madgui/widget/tableview.py
madgui-20.10.0.dist-info/COPYING.rst
madgui-20.10.0.dist-info/METADATA
madgui-20.10.0.dist-info/WHEEL
madgui-20.10.0.dist-info/entry_points.txt
madgui-20.10.0.dist-info/top_level.txt
madgui-20.10.0.dist-info/zip-safe
madgui-20.10.0.dist-info/RECORD
