Metadata-Version: 2.1
Name: madgui
Version: 20.10.0
Summary: GUI for accelerator simulations using MAD-X.
Home-page: https://github.com/hibtc/madgui
Author: Thomas Gläßle
Author-email: t_glaessle@gmx.de
Maintainer: Cristopher Cortés
Maintainer-email: ecortesg95@gmail.com
License: GPLv3+
Platform: UNKNOWN
Classifier: Development Status :: 3 - Alpha
Classifier: Environment :: X11 Applications :: Qt
Classifier: Intended Audience :: Developers
Classifier: Intended Audience :: Science/Research
Classifier: License :: OSI Approved :: GNU General Public License v3 or later (GPLv3+)
Classifier: Operating System :: OS Independent
Classifier: Programming Language :: Python :: 3
Classifier: Topic :: Scientific/Engineering :: Medical Science Apps.
Classifier: Topic :: Scientific/Engineering :: Physics
Requires-Python: >=3.6
Requires-Dist: cpymad (>=1.4.1)
Requires-Dist: docopt
Requires-Dist: matplotlib (==3.1.3)
Requires-Dist: numpy
Requires-Dist: scipy
Requires-Dist: PyYAML
Requires-Dist: PyQt5 (==5.12.3)
Requires-Dist: Pint (>=0.9)
Requires-Dist: docutils
Requires-Dist: importlib-resources (>=0.3)
Requires-Dist: pyqtconsole (==1.2.1)
Requires-Dist: jedi
Requires-Dist: PyOpenGL
Requires-Dist: sphinx (==2.4.2)
